rtl/random.v
/*module random(rst,clk,random_out);
input clk, rst;
output reg [13:0]random_out;
integer i;//a parameter		
always@(negedge clk)
begin
i=i+1;//random data precent times
if(rst==1'b1)
	random_out=14'd4;//original datas
else if(random_out<14'd3000)
	random_out=random_out/3+random_out;
	//generate equation of random datas
else if(random_out>14'd3000)
	random_out=i;
	//prevent random datas from largger
if(i>500)
i=1;//prevent times from largger
end
endmodule
*/
module random(rst,clk,random_out);
input clk, rst;
output reg [13:0]random_out;


reg [5:0] counter;
wire [5:0] temp = {counter[0], counter[5], counter[1], counter[4], counter[2], counter[3]};
wire [5:0] temp_1 = {counter[1], counter[4], counter[2], counter[3], counter[0], counter[5]};


always@(posedge clk, posedge rst)
begin

if(rst)
	random_out <= 14'd0;//original datas
else if (counter == 6'd32)
	random_out <= {random_out[13:0], counter[0]};
else 
	random_out <= {counter[0], counter[5],temp, temp_1} + random_out;

end


always@(posedge clk, posedge rst)
begin
	if(rst) 
		counter <= 6'd0;
	else 
		counter <= counter + 6'd3;
end





endmodule

rtl/frogg.v
module frogg(clk,rst,go,back,frog,reset);
input reset,clk,go,rst,back;
output reg [18:0]frog;
parameter s0=5'd0,s1=5'd1,s2=5'd2,s3=5'd3,s12=5'd12;
parameter s4=5'd4,s5=5'd5,s6=5'd6,s7=5'd7,s13=5'd13;
parameter s8=5'd8,s9=5'd9,s10=5'd10,s17=5'd17,s11=5'd11;
parameter s14=5'd14,s15=5'd15,s16=5'd16,s18=5'd18;
reg [4:0]state;
integer i;//a parameter	
always@(posedge clk)
begin
if(rst==1'b1||reset==1'b1)
	state=5'b00000;//initialize
if(go==1'b0&&i==1)
	begin//when go_bottom run
	state=state+5'b00001;
	i=2;//prevent repeat actions
	end
if(back==1'b0&&i==1)
	begin//when back_bottom run
	state=state-5'b00001;
	i=2;//prevent repeat actions
	end
if(back==1'b1&&go==1'b1)
	i=1;//the next bottom is available
case(state)//the saturation of the frog 
	s0: frog=19'b0000000000000000001;
	s1: frog=19'b0000000000000000010;
	s2: frog=19'b0000000000000000100;
	s3: frog=19'b0000000000000001000;
	s4: frog=19'b0000000000000010000;
	s5: frog=19'b0000000000000100000;
	s6: frog=19'b0000000000001000000;
	s7: frog=19'b0000000000010000000;
	s8: frog=19'b0000000000100000000;
	s9: frog=19'b0000000001000000000;
	s10:frog=19'b0000000010000000000;
	s11:frog=19'b0000000100000000000;
	s12:frog=19'b0000001000000000000;
	s13:frog=19'b0000010000000000000;
	s14:frog=19'b0000100000000000000;
	s15:frog=19'b0001000000000000000;
	s16:frog=19'b0010000000000000000;
	s17:frog=19'b0100000000000000000;
	s18:frog=19'b1000000000000000000;
endcase
end
endmodule

rtl/division.v
/*module division (oclk, clk);//1 second
input clk;
output oclk;
reg oclk;
integer i;//a parameter								
always @ (negedge clk)
	if (i<=25000000)//1st 0.5 period 						
		begin
		i=i+1;
		oclk=oclk;//original
		end
	else if(i==25000001)//2nd 0.5 period 					
		begin
		oclk=~oclk;//change
		i=0;//reset parameter 
		end
endmodule
*/
module division (oclk, clk, rst);//1 second
input clk, rst;
output oclk;
reg oclk;

reg [24:0]counter;

always @ (posedge clk, posedge rst)
begin
	if (rst)
		counter <= 25'd0;
	else if (counter == 25'd250)
		counter <= 25'd0;
	else
		counter <= counter + 25'd1;
end

always@ (posedge clk, posedge rst)
begin
	if(rst)
		oclk <= 1'd0;
	else if (counter == 25'd249)
		oclk <= ~oclk;
	else
		oclk <= oclk;
end


endmodule

rtl/ex1.v
module ex1(clk,rst,go_1,go_2,back_1,back_2,
			outview,light_1,light_2,);
input clk,go_1,go_2,back_1,back_2,rst;
output [17:0]outview;//real output
output reg [3:0]light_1,light_2;
wire [18:0]frog_1,frog_2,block;
wire [18:0]byoutview;//common lights
wire [18:0]die_1,die_2;
wire [13:0] random_out;
wire oclk;
division division(oclk, clk, rst);//divided freq. to 1 second
frogg f1(clk,rst,go_1,back_1,frog_1,reset_1);
frogg f2(clk,rst,go_2,back_2,frog_2,reset_2);
random rr1(rst,oclk,random_out);//random 0.5 second
assign block={1'b0,random_out[3],1'b0,random_out[7],
				1'b0,random_out[1],1'b0,random_out[5],
				1'b0,random_out[4],1'b0,random_out[8],
				1'b0,random_out[2],1'b0,random_out[6],
				1'b0,random_out[0],1'b0};//random block
assign die_1=frog_1&block;//whether frog1 bomb into block or not
assign die_2=frog_2&block;//whether frog2 bomb into block or not
assign byoutview = frog_1 | block | frog_2 ;//common lights
assign outview=byoutview[17:0];//real output
reg reset_1,reset_2;//let the frog saturation back to original
always@(posedge clk, posedge rst)
begin
if(rst==1'b1)
	begin//initialize
	light_1=4'b0111;
	light_2=4'b0111;
	reset_1=1'b0;
	reset_2=1'b0;
	end
if(die_1!=19'd0)
	begin//frog1 bomb into block
	light_1={1'b0,light_1[3:1]};//decrease a light1
	reset_1=1'b1;//frog1 back to original
	end
else if(die_1==19'd0)
	reset_1=1'b0;//frog1 can go or back
if(die_2!=19'd0)
	begin//frog2 bomb into block
	light_2={1'b0,light_2[3:1]};//decrease a light2
	reset_2=1'b1;//frog2 back to original
	end
else if(die_2==19'd0)
	reset_2=1'b0;//frog2 can go or back
if(frog_1==19'b1000000000000000000)
begin
light_1=4'b1111;//frog1 win
light_2=4'b0000;
end
if(frog_2==19'b1000000000000000000)
begin
light_1=4'b0000;
light_2=4'b1111;//frog2 win
end
end
endmodule

rtl/test_bench.v
`timescale 1ns/1ps
`define CYCLE 100
module test_bench ();

//**************************** wire & reg**********************//
initial begin
    $display("//***************************************");
    $display("//==top input : clk, go_1, go_2, back_1, back_2, rst");
    $display("//==top output : outview, light_1, light_2");
    $display("//***************************************");
    end
reg clk,go_1,go_2,back_1,back_2,rst;
wire [17:0]outview;
wire [3:0]light_1,light_2;

//**************************** module **********************//
initial begin
    $display("===module : add");
    end
ex1 ex1(.clk(clk),
		.rst(rst),
		.go_1(go_1),
		.go_2(go_2),
		.back_1(back_1),
		.back_2(back_2),
		.outview(outview),
		.light_1(light_1),
		.light_2(light_2)
);

//**************************** clock gen **********************//
initial begin
	$display("===starting generating clk");
	force clk = 1'b0;
	forever #(`CYCLE/2) force clk = ~clk;
    end

//**************************** initial and wavegen **********************//
initial begin
	$display("===starting dump waveform");
	$dumpfile("dump.vcd");
	$dumpvars(0,ex1);
end

initial begin
    go_1 = 0;
    go_2 = 0;
	back_1 = 0;
	back_1 = 2;	
    end

//**************************** main **********************//
reg [13:0]index_2;
initial begin

	RESET;

	for(index_2 = 14'd0; index_2 < 14'd4; index_2 = index_2 + 14'd1) begin 
        #1000;
        $display("send : 0x%h, 0x%h" , index_2, index_2 + 14'd1);

        end


	$display("===all done");
	#10_000_000; $finish;
    end



task RESET;
begin
	force rst = 1'b0;
	#1_000;
	force rst = 1'b1;
	#1_000;
	force rst = 1'b0;
	#1_000;
end
endtask






endmodule

dump.vcd
$date
	Sat Aug 25 19:55:07 2018
$end
$version
	Icarus Verilog
$end
$timescale
	1ps
$end
$scope module test_bench $end
$scope module ex1 $end
$var wire 1 ! back_1 $end
$var wire 1 " back_2 $end
$var wire 19 # block [18:0] $end
$var wire 19 $ byoutview [18:0] $end
$var wire 1 % clk $end
$var wire 19 & die_1 [18:0] $end
$var wire 19 ' die_2 [18:0] $end
$var wire 19 ( frog_1 [18:0] $end
$var wire 19 ) frog_2 [18:0] $end
$var wire 1 * go_1 $end
$var wire 1 + go_2 $end
$var wire 1 , oclk $end
$var wire 18 - outview [17:0] $end
$var wire 14 . random_out [13:0] $end
$var wire 1 / rst $end
$var reg 4 0 light_1 [3:0] $end
$var reg 4 1 light_2 [3:0] $end
$var reg 1 2 reset_1 $end
$var reg 1 3 reset_2 $end
$scope module division $end
$var wire 1 % clk $end
$var wire 1 / rst $end
$var reg 25 4 counter [24:0] $end
$var reg 1 5 oclk $end
$upscope $end
$scope module f1 $end
$var wire 1 ! back $end
$var wire 1 % clk $end
$var wire 1 * go $end
$var wire 1 6 reset $end
$var wire 1 / rst $end
$var reg 19 7 frog [18:0] $end
$var integer 32 8 i [31:0] $end
$var reg 5 9 state [4:0] $end
$upscope $end
$scope module f2 $end
$var wire 1 " back $end
$var wire 1 % clk $end
$var wire 1 + go $end
$var wire 1 : reset $end
$var wire 1 / rst $end
$var reg 19 ; frog [18:0] $end
$var integer 32 < i [31:0] $end
$var reg 5 = state [4:0] $end
$upscope $end
$scope module rr1 $end
$var wire 1 , clk $end
$var wire 1 / rst $end
$var wire 6 > temp [5:0] $end
$var wire 6 ? temp_1 [5:0] $end
$var reg 6 @ counter [5:0] $end
$var reg 14 A random_out [13:0] $end
$upscope $end
$upscope $end
$upscope $end
$enddefinitions $end
#0
$dumpvars
bx A
bx @
bx ?
bx >
bx =
bx <
bx ;
x:
bx 9
bx 8
bx 7
x6
x5
bx 4
x3
x2
bx 1
bx 0
0/
bx .
bx -
x,
0+
0*
bx )
bx (
b0x0x0x0x0x0x0x0x0x0 '
b0x0x0x0x0x0x0x0x0x0 &
0%
bx $
b0x0x0x0x0x0x0x0x0x0 #
x"
0!
$end
#50000
1%
#100000
0%
#150000
1%
#200000
0%
#250000
1%
#300000
0%
#350000
1%
#400000
0%
#450000
1%
#500000
0%
#550000
1%
#600000
0%
#650000
1%
#700000
0%
#750000
1%
#800000
0%
#850000
1%
#900000
0%
#950000
1%
#1000000
b0 '
b0 &
b0 #
b0 >
b0 ?
b0 A
b0 .
b0 @
b0 4
05
0,
03
0:
02
06
b111 1
b111 0
0%
1/
#1050000
b1 -
b1 $
b1 7
b1 (
b0 9
b1 ;
b1 )
b0 =
1%
#1100000
0%
#1150000
1%
#1200000
0%
#1250000
1%
#1300000
0%
#1350000
1%
#1400000
0%
#1450000
1%
#1500000
0%
#1550000
1%
#1600000
0%
#1650000
1%
#1700000
0%
#1750000
1%
#1800000
0%
#1850000
1%
#1900000
0%
#1950000
1%
#2000000
0%
0/
#2050000
b1 4
1%
#2100000
0%
#2150000
b10 4
1%
#2200000
0%
#2250000
b11 4
1%
#2300000
0%
#2350000
b100 4
1%
#2400000
0%
#2450000
b101 4
1%
#2500000
0%
#2550000
b110 4
1%
#2600000
0%
#2650000
b111 4
1%
#2700000
0%
#2750000
b1000 4
1%
#2800000
0%
#2850000
b1001 4
1%
#2900000
0%
#2950000
b1010 4
1%
#3000000
0%
#3050000
b1011 4
1%
#3100000
0%
#3150000
b1100 4
1%
#3200000
0%
#3250000
b1101 4
1%
#3300000
0%
#3350000
b1110 4
1%
#3400000
0%
#3450000
b1111 4
1%
#3500000
0%
#3550000
b10000 4
1%
#3600000
0%
#3650000
b10001 4
1%
#3700000
0%
#3750000
b10010 4
1%
#3800000
0%
#3850000
b10011 4
1%
#3900000
0%
#3950000
b10100 4
1%
#4000000
0%
#4050000
b10101 4
1%
#4100000
0%
#4150000
b10110 4
1%
#4200000
0%
#4250000
b10111 4
1%
#4300000
0%
#4350000
b11000 4
1%
#4400000
0%
#4450000
b11001 4
1%
#4500000
0%
#4550000
b11010 4
1%
#4600000
0%
#4650000
b11011 4
1%
#4700000
0%
#4750000
b11100 4
1%
#4800000
0%
#4850000
b11101 4
1%
#4900000
0%
#4950000
b11110 4
1%
#5000000
0%
#5050000
b11111 4
1%
#5100000
0%
#5150000
b100000 4
1%
#5200000
0%
#5250000
b100001 4
1%
#5300000
0%
#5350000
b100010 4
1%
#5400000
0%
#5450000
b100011 4
1%
#5500000
0%
#5550000
b100100 4
1%
#5600000
0%
#5650000
b100101 4
1%
#5700000
0%
#5750000
b100110 4
1%
#5800000
0%
#5850000
b100111 4
1%
#5900000
0%
#5950000
b101000 4
1%
#6000000
0%
#6050000
b101001 4
1%
#6100000
0%
#6150000
b101010 4
1%
#6200000
0%
#6250000
b101011 4
1%
#6300000
0%
#6350000
b101100 4
1%
#6400000
0%
#6450000
b101101 4
1%
#6500000
0%
#6550000
b101110 4
1%
#6600000
0%
#6650000
b101111 4
1%
#6700000
0%
#6750000
b110000 4
1%
#6800000
0%
#6850000
b110001 4
1%
#6900000
0%
#6950000
b110010 4
1%
#7000000
0%
#7050000
b110011 4
1%
#7100000
0%
#7150000
b110100 4
1%
#7200000
0%
#7250000
b110101 4
1%
#7300000
0%
#7350000
b110110 4
1%
#7400000
0%
#7450000
b110111 4
1%
#7500000
0%
#7550000
b111000 4
1%
#7600000
0%
#7650000
b111001 4
1%
#7700000
0%
#7750000
b111010 4
1%
#7800000
0%
#7850000
b111011 4
1%
#7900000
0%
#7950000
b111100 4
1%
#8000000
0%
#8050000
b111101 4
1%
#8100000
0%
#8150000
b111110 4
1%
#8200000
0%
#8250000
b111111 4
1%
#8300000
0%
#8350000
b1000000 4
1%
#8400000
0%
#8450000
b1000001 4
1%
#8500000
0%
#8550000
b1000010 4
1%
#8600000
0%
#8650000
b1000011 4
1%
#8700000
0%
#8750000
b1000100 4
1%
#8800000
0%
#8850000
b1000101 4
1%
#8900000
0%
#8950000
b1000110 4
1%
#9000000
0%
#9050000
b1000111 4
1%
#9100000
0%
#9150000
b1001000 4
1%
#9200000
0%
#9250000
b1001001 4
1%
#9300000
0%
#9350000
b1001010 4
1%
#9400000
0%
#9450000
b1001011 4
1%
#9500000
0%
#9550000
b1001100 4
1%
#9600000
0%
#9650000
b1001101 4
1%
#9700000
0%
#9750000
b1001110 4
1%
#9800000
0%
#9850000
b1001111 4
1%
#9900000
0%
#9950000
b1010000 4
1%
#10000000
0%
#10050000
b1010001 4
1%
#10100000
0%
#10150000
b1010010 4
1%
#10200000
0%
#10250000
b1010011 4
1%
#10300000
0%
#10350000
b1010100 4
1%
#10400000
0%
#10450000
b1010101 4
1%
#10500000
0%
#10550000
b1010110 4
1%
#10600000
0%
#10650000
b1010111 4
1%
#10700000
0%
#10750000
b1011000 4
1%
#10800000
0%
#10850000
b1011001 4
1%
#10900000
0%
#10950000
b1011010 4
1%
#11000000
0%
#11050000
b1011011 4
1%
#11100000
0%
#11150000
b1011100 4
1%
#11200000
0%
#11250000
b1011101 4
1%
#11300000
0%
#11350000
b1011110 4
1%
#11400000
0%
#11450000
b1011111 4
1%
#11500000
0%
#11550000
b1100000 4
1%
#11600000
0%
#11650000
b1100001 4
1%
#11700000
0%
#11750000
b1100010 4
1%
#11800000
0%
#11850000
b1100011 4
1%
#11900000
0%
#11950000
b1100100 4
1%
#12000000
0%
#12050000
b1100101 4
1%
#12100000
0%
#12150000
b1100110 4
1%
#12200000
0%
#12250000
b1100111 4
1%
#12300000
0%
#12350000
b1101000 4
1%
#12400000
0%
#12450000
b1101001 4
1%
#12500000
0%
#12550000
b1101010 4
1%
#12600000
0%
#12650000
b1101011 4
1%
#12700000
0%
#12750000
b1101100 4
1%
#12800000
0%
#12850000
b1101101 4
1%
#12900000
0%
#12950000
b1101110 4
1%
#13000000
0%
#13050000
b1101111 4
1%
#13100000
0%
#13150000
b1110000 4
1%
#13200000
0%
#13250000
b1110001 4
1%
#13300000
0%
#13350000
b1110010 4
1%
#13400000
0%
#13450000
b1110011 4
1%
#13500000
0%
#13550000
b1110100 4
1%
#13600000
0%
#13650000
b1110101 4
1%
#13700000
0%
#13750000
b1110110 4
1%
#13800000
0%
#13850000
b1110111 4
1%
#13900000
0%
#13950000
b1111000 4
1%
#14000000
0%
#14050000
b1111001 4
1%
#14100000
0%
#14150000
b1111010 4
1%
#14200000
0%
#14250000
b1111011 4
1%
#14300000
0%
#14350000
b1111100 4
1%
#14400000
0%
#14450000
b1111101 4
1%
#14500000
0%
#14550000
b1111110 4
1%
#14600000
0%
#14650000
b1111111 4
1%
#14700000
0%
#14750000
b10000000 4
1%
#14800000
0%
#14850000
b10000001 4
1%
#14900000
0%
#14950000
b10000010 4
1%
#15000000
0%
#15050000
b10000011 4
1%
#15100000
0%
#15150000
b10000100 4
1%
#15200000
0%
#15250000
b10000101 4
1%
#15300000
0%
#15350000
b10000110 4
1%
#15400000
0%
#15450000
b10000111 4
1%
#15500000
0%
#15550000
b10001000 4
1%
#15600000
0%
#15650000
b10001001 4
1%
#15700000
0%
#15750000
b10001010 4
1%
#15800000
0%
#15850000
b10001011 4
1%
#15900000
0%
#15950000
b10001100 4
1%
#16000000
0%
#16050000
b10001101 4
1%
#16100000
0%
#16150000
b10001110 4
1%
#16200000
0%
#16250000
b10001111 4
1%
#16300000
0%
#16350000
b10010000 4
1%
#16400000
0%
#16450000
b10010001 4
1%
#16500000
0%
#16550000
b10010010 4
1%
#16600000
0%
#16650000
b10010011 4
1%
#16700000
0%
#16750000
b10010100 4
1%
#16800000
0%
#16850000
b10010101 4
1%
#16900000
0%
#16950000
b10010110 4
1%
#17000000
0%
#17050000
b10010111 4
1%
#17100000
0%
#17150000
b10011000 4
1%
#17200000
0%
#17250000
b10011001 4
1%
#17300000
0%
#17350000
b10011010 4
1%
#17400000
0%
#17450000
b10011011 4
1%
#17500000
0%
#17550000
b10011100 4
1%
#17600000
0%
#17650000
b10011101 4
1%
#17700000
0%
#17750000
b10011110 4
1%
#17800000
0%
#17850000
b10011111 4
1%
#17900000
0%
#17950000
b10100000 4
1%
#18000000
0%
#18050000
b10100001 4
1%
#18100000
0%
#18150000
b10100010 4
1%
#18200000
0%
#18250000
b10100011 4
1%
#18300000
0%
#18350000
b10100100 4
1%
#18400000
0%
#18450000
b10100101 4
1%
#18500000
0%
#18550000
b10100110 4
1%
#18600000
0%
#18650000
b10100111 4
1%
#18700000
0%
#18750000
b10101000 4
1%
#18800000
0%
#18850000
b10101001 4
1%
#18900000
0%
#18950000
b10101010 4
1%
#19000000
0%
#19050000
b10101011 4
1%
#19100000
0%
#19150000
b10101100 4
1%
#19200000
0%
#19250000
b10101101 4
1%
#19300000
0%
#19350000
b10101110 4
1%
#19400000
0%
#19450000
b10101111 4
1%
#19500000
0%
#19550000
b10110000 4
1%
#19600000
0%
#19650000
b10110001 4
1%
#19700000
0%
#19750000
b10110010 4
1%
#19800000
0%
#19850000
b10110011 4
1%
#19900000
0%
#19950000
b10110100 4
1%
#20000000
0%
#20050000
b10110101 4
1%
#20100000
0%
#20150000
b10110110 4
1%
#20200000
0%
#20250000
b10110111 4
1%
#20300000
0%
#20350000
b10111000 4
1%
#20400000
0%
#20450000
b10111001 4
1%
#20500000
0%
#20550000
b10111010 4
1%
#20600000
0%
#20650000
b10111011 4
1%
#20700000
0%
#20750000
b10111100 4
1%
#20800000
0%
#20850000
b10111101 4
1%
#20900000
0%
#20950000
b10111110 4
1%
#21000000
0%
#21050000
b10111111 4
1%
#21100000
0%
#21150000
b11000000 4
1%
#21200000
0%
#21250000
b11000001 4
1%
#21300000
0%
#21350000
b11000010 4
1%
#21400000
0%
#21450000
b11000011 4
1%
#21500000
0%
#21550000
b11000100 4
1%
#21600000
0%
#21650000
b11000101 4
1%
#21700000
0%
#21750000
b11000110 4
1%
#21800000
0%
#21850000
b11000111 4
1%
#21900000
0%
#21950000
b11001000 4
1%
#22000000
0%
#22050000
b11001001 4
1%
#22100000
0%
#22150000
b11001010 4
1%
#22200000
0%
#22250000
b11001011 4
1%
#22300000
0%
#22350000
b11001100 4
1%
#22400000
0%
#22450000
b11001101 4
1%
#22500000
0%
#22550000
b11001110 4
1%
#22600000
0%
#22650000
b11001111 4
1%
#22700000
0%
#22750000
b11010000 4
1%
#22800000
0%
#22850000
b11010001 4
1%
#22900000
0%
#22950000
b11010010 4
1%
#23000000
0%
#23050000
b11010011 4
1%
#23100000
0%
#23150000
b11010100 4
1%
#23200000
0%
#23250000
b11010101 4
1%
#23300000
0%
#23350000
b11010110 4
1%
#23400000
0%
#23450000
b11010111 4
1%
#23500000
0%
#23550000
b11011000 4
1%
#23600000
0%
#23650000
b11011001 4
1%
#23700000
0%
#23750000
b11011010 4
1%
#23800000
0%
#23850000
b11011011 4
1%
#23900000
0%
#23950000
b11011100 4
1%
#24000000
0%
#24050000
b11011101 4
1%
#24100000
0%
#24150000
b11011110 4
1%
#24200000
0%
#24250000
b11011111 4
1%
#24300000
0%
#24350000
b11100000 4
1%
#24400000
0%
#24450000
b11100001 4
1%
#24500000
0%
#24550000
b11100010 4
1%
#24600000
0%
#24650000
b11100011 4
1%
#24700000
0%
#24750000
b11100100 4
1%
#24800000
0%
#24850000
b11100101 4
1%
#24900000
0%
#24950000
b11100110 4
1%
#25000000
0%
#25050000
b11100111 4
1%
#25100000
0%
#25150000
b11101000 4
1%
#25200000
0%
#25250000
b11101001 4
1%
#25300000
0%
#25350000
b11101010 4
1%
#25400000
0%
#25450000
b11101011 4
1%
#25500000
0%
#25550000
b11101100 4
1%
#25600000
0%
#25650000
b11101101 4
1%
#25700000
0%
#25750000
b11101110 4
1%
#25800000
0%
#25850000
b11101111 4
1%
#25900000
0%
#25950000
b11110000 4
1%
#26000000
0%
#26050000
b11110001 4
1%
#26100000
0%
#26150000
b11110010 4
1%
#26200000
0%
#26250000
b11110011 4
1%
#26300000
0%
#26350000
b11110100 4
1%
#26400000
0%
#26450000
b11110101 4
1%
#26500000
0%
#26550000
b11110110 4
1%
#26600000
0%
#26650000
b11110111 4
1%
#26700000
0%
#26750000
b11111000 4
1%
#26800000
0%
#26850000
b11111001 4
1%
#26900000
0%
#26950000
b101000 >
b100010 ?
b11 @
b11111010 4
15
1,
1%
#27000000
0%
#27050000
b0 4
1%
#27100000
0%
#27150000
b1 4
1%
#27200000
0%
#27250000
b10 4
1%
#27300000
0%
#27350000
b11 4
1%
#27400000
0%
#27450000
b100 4
1%
#27500000
0%
#27550000
b101 4
1%
#27600000
0%
#27650000
b110 4
1%
#27700000
0%
#27750000
b111 4
1%
#27800000
0%
#27850000
b1000 4
1%
#27900000
0%
#27950000
b1001 4
1%
#28000000
0%
#28050000
b1010 4
1%
#28100000
0%
#28150000
b1011 4
1%
#28200000
0%
#28250000
b1100 4
1%
#28300000
0%
#28350000
b1101 4
1%
#28400000
0%
#28450000
b1110 4
1%
#28500000
0%
#28550000
b1111 4
1%
#28600000
0%
#28650000
b10000 4
1%
#28700000
0%
#28750000
b10001 4
1%
#28800000
0%
#28850000
b10010 4
1%
#28900000
0%
#28950000
b10011 4
1%
#29000000
0%
#29050000
b10100 4
1%
#29100000
0%
#29150000
b10101 4
1%
#29200000
0%
#29250000
b10110 4
1%
#29300000
0%
#29350000
b10111 4
1%
#29400000
0%
#29450000
b11000 4
1%
#29500000
0%
#29550000
b11001 4
1%
#29600000
0%
#29650000
b11010 4
1%
#29700000
0%
#29750000
b11011 4
1%
#29800000
0%
#29850000
b11100 4
1%
#29900000
0%
#29950000
b11101 4
1%
#30000000
0%
#30050000
b11110 4
1%
#30100000
0%
#30150000
b11111 4
1%
#30200000
0%
#30250000
b100000 4
1%
#30300000
0%
#30350000
b100001 4
1%
#30400000
0%
#30450000
b100010 4
1%
#30500000
0%
#30550000
b100011 4
1%
#30600000
0%
#30650000
b100100 4
1%
#30700000
0%
#30750000
b100101 4
1%
#30800000
0%
#30850000
b100110 4
1%
#30900000
0%
#30950000
b100111 4
1%
#31000000
0%
#31050000
b101000 4
1%
#31100000
0%
#31150000
b101001 4
1%
#31200000
0%
#31250000
b101010 4
1%
#31300000
0%
#31350000
b101011 4
1%
#31400000
0%
#31450000
b101100 4
1%
#31500000
0%
#31550000
b101101 4
1%
#31600000
0%
#31650000
b101110 4
1%
#31700000
0%
#31750000
b101111 4
1%
#31800000
0%
#31850000
b110000 4
1%
#31900000
0%
#31950000
b110001 4
1%
#32000000
0%
#32050000
b110010 4
1%
#32100000
0%
#32150000
b110011 4
1%
#32200000
0%
#32250000
b110100 4
1%
#32300000
0%
#32350000
b110101 4
1%
#32400000
0%
#32450000
b110110 4
1%
#32500000
0%
#32550000
b110111 4
1%
#32600000
0%
#32650000
b111000 4
1%
#32700000
0%
#32750000
b111001 4
1%
#32800000
0%
#32850000
b111010 4
1%
#32900000
0%
#32950000
b111011 4
1%
#33000000
0%
#33050000
b111100 4
1%
#33100000
0%
#33150000
b111101 4
1%
#33200000
0%
#33250000
b111110 4
1%
#33300000
0%
#33350000
b111111 4
1%
#33400000
0%
#33450000
b1000000 4
1%
#33500000
0%
#33550000
b1000001 4
1%
#33600000
0%
#33650000
b1000010 4
1%
#33700000
0%
#33750000
b1000011 4
1%
#33800000
0%
#33850000
b1000100 4
1%
#33900000
0%
#33950000
b1000101 4
1%
#34000000
0%
#34050000
b1000110 4
1%
#34100000
0%
#34150000
b1000111 4
1%
#34200000
0%
#34250000
b1001000 4
1%
#34300000
0%
#34350000
b1001001 4
1%
#34400000
0%
#34450000
b1001010 4
1%
#34500000
0%
#34550000
b1001011 4
1%
#34600000
0%
#34650000
b1001100 4
1%
#34700000
0%
#34750000
b1001101 4
1%
#34800000
0%
#34850000
b1001110 4
1%
#34900000
0%
#34950000
b1001111 4
1%
#35000000
0%
#35050000
b1010000 4
1%
#35100000
0%
#35150000
b1010001 4
1%
#35200000
0%
#35250000
b1010010 4
1%
#35300000
0%
#35350000
b1010011 4
1%
#35400000
0%
#35450000
b1010100 4
1%
#35500000
0%
#35550000
b1010101 4
1%
#35600000
0%
#35650000
b1010110 4
1%
#35700000
0%
#35750000
b1010111 4
1%
#35800000
0%
#35850000
b1011000 4
1%
#35900000
0%
#35950000
b1011001 4
1%
#36000000
0%
#36050000
b1011010 4
1%
#36100000
0%
#36150000
b1011011 4
1%
#36200000
0%
#36250000
b1011100 4
1%
#36300000
0%
#36350000
b1011101 4
1%
#36400000
0%
#36450000
b1011110 4
1%
#36500000
0%
#36550000
b1011111 4
1%
#36600000
0%
#36650000
b1100000 4
1%
#36700000
0%
#36750000
b1100001 4
1%
#36800000
0%
#36850000
b1100010 4
1%
#36900000
0%
#36950000
b1100011 4
1%
#37000000
0%
#37050000
b1100100 4
1%
#37100000
0%
#37150000
b1100101 4
1%
#37200000
0%
#37250000
b1100110 4
1%
#37300000
0%
#37350000
b1100111 4
1%
#37400000
0%
#37450000
b1101000 4
1%
#37500000
0%
#37550000
b1101001 4
1%
#37600000
0%
#37650000
b1101010 4
1%
#37700000
0%
#37750000
b1101011 4
1%
#37800000
0%
#37850000
b1101100 4
1%
#37900000
0%
#37950000
b1101101 4
1%
#38000000
0%
#38050000
b1101110 4
1%
#38100000
0%
#38150000
b1101111 4
1%
#38200000
0%
#38250000
b1110000 4
1%
#38300000
0%
#38350000
b1110001 4
1%
#38400000
0%
#38450000
b1110010 4
1%
#38500000
0%
#38550000
b1110011 4
1%
#38600000
0%
#38650000
b1110100 4
1%
#38700000
0%
#38750000
b1110101 4
1%
#38800000
0%
#38850000
b1110110 4
1%
#38900000
0%
#38950000
b1110111 4
1%
#39000000
0%
#39050000
b1111000 4
1%
#39100000
0%
#39150000
b1111001 4
1%
#39200000
0%
#39250000
b1111010 4
1%
#39300000
0%
#39350000
b1111011 4
1%
#39400000
0%
#39450000
b1111100 4
1%
#39500000
0%
#39550000
b1111101 4
1%
#39600000
0%
#39650000
b1111110 4
1%
#39700000
0%
#39750000
b1111111 4
1%
#39800000
0%
#39850000
b10000000 4
1%
#39900000
0%
#39950000
b10000001 4
1%
#40000000
0%
#40050000
b10000010 4
1%
#40100000
0%
#40150000
b10000011 4
1%
#40200000
0%
#40250000
b10000100 4
1%
#40300000
0%
#40350000
b10000101 4
1%
#40400000
0%
#40450000
b10000110 4
1%
#40500000
0%
#40550000
b10000111 4
1%
#40600000
0%
#40650000
b10001000 4
1%
#40700000
0%
#40750000
b10001001 4
1%
#40800000
0%
#40850000
b10001010 4
1%
#40900000
0%
#40950000
b10001011 4
1%
#41000000
0%
#41050000
b10001100 4
1%
#41100000
0%
#41150000
b10001101 4
1%
#41200000
0%
#41250000
b10001110 4
1%
#41300000
0%
#41350000
b10001111 4
1%
#41400000
0%
#41450000
b10010000 4
1%
#41500000
0%
#41550000
b10010001 4
1%
#41600000
0%
#41650000
b10010010 4
1%
#41700000
0%
#41750000
b10010011 4
1%
#41800000
0%
#41850000
b10010100 4
1%
#41900000
0%
#41950000
b10010101 4
1%
#42000000
0%
#42050000
b10010110 4
1%
#42100000
0%
#42150000
b10010111 4
1%
#42200000
0%
#42250000
b10011000 4
1%
#42300000
0%
#42350000
b10011001 4
1%
#42400000
0%
#42450000
b10011010 4
1%
#42500000
0%
#42550000
b10011011 4
1%
#42600000
0%
#42650000
b10011100 4
1%
#42700000
0%
#42750000
b10011101 4
1%
#42800000
0%
#42850000
b10011110 4
1%
#42900000
0%
#42950000
b10011111 4
1%
#43000000
0%
#43050000
b10100000 4
1%
#43100000
0%
#43150000
b10100001 4
1%
#43200000
0%
#43250000
b10100010 4
1%
#43300000
0%
#43350000
b10100011 4
1%
#43400000
0%
#43450000
b10100100 4
1%
#43500000
0%
#43550000
b10100101 4
1%
#43600000
0%
#43650000
b10100110 4
1%
#43700000
0%
#43750000
b10100111 4
1%
#43800000
0%
#43850000
b10101000 4
1%
#43900000
0%
#43950000
b10101001 4
1%
#44000000
0%
#44050000
b10101010 4
1%
#44100000
0%
#44150000
b10101011 4
1%
#44200000
0%
#44250000
b10101100 4
1%
#44300000
0%
#44350000
b10101101 4
1%
#44400000
0%
#44450000
b10101110 4
1%
#44500000
0%
#44550000
b10101111 4
1%
#44600000
0%
#44650000
b10110000 4
1%
#44700000
0%
#44750000
b10110001 4
1%
#44800000
0%
#44850000
b10110010 4
1%
#44900000
0%
#44950000
b10110011 4
1%
#45000000
0%
#45050000
b10110100 4
1%
#45100000
0%
#45150000
b10110101 4
1%
#45200000
0%
#45250000
b10110110 4
1%
#45300000
0%
#45350000
b10110111 4
1%
#45400000
0%
#45450000
b10111000 4
1%
#45500000
0%
#45550000
b10111001 4
1%
#45600000
0%
#45650000
b10111010 4
1%
#45700000
0%
#45750000
b10111011 4
1%
#45800000
0%
#45850000
b10111100 4
1%
#45900000
0%
#45950000
b10111101 4
1%
#46000000
0%
#46050000
b10111110 4
1%
#46100000
0%
